Metadata-Version: 2.1
Name: removebg_infusiblecoder
Version: 0.0.15
Summary: Remove image background
Home-page: https://github.com/syedusama5556/removebg_infusiblecoder
Author: Syed Usama Ahmad
Author-email: syedusama5556@gmail.com
Keywords: remove,background,u2net
Classifier: License :: OSI Approved :: MIT License
Classifier: Topic :: Scientific/Engineering
Classifier: Topic :: Scientific/Engineering :: Mathematics
Classifier: Topic :: Scientific/Engineering :: Artificial Intelligence
Classifier: Topic :: Software Development
Classifier: Topic :: Software Development :: Libraries
Classifier: Topic :: Software Development :: Libraries :: Python Modules
Classifier: Programming Language :: Python
Classifier: Programming Language :: Python :: 3 :: Only
Classifier: Programming Language :: Python :: 3.9
Classifier: Programming Language :: Python :: 3.10
Classifier: Programming Language :: Python :: 3.11
Classifier: Programming Language :: Python :: 3.12
Requires-Python: >=3.9, <3.13
License-File: LICENSE.txt
Requires-Dist: carvekit
Requires-Dist: jsonschema
Requires-Dist: numpy
Requires-Dist: onnxruntime
Requires-Dist: opencv-contrib-python-headless
Requires-Dist: pillow
Requires-Dist: pooch
Requires-Dist: pymatting
Requires-Dist: scikit-image
Requires-Dist: scipy
Requires-Dist: tqdm
Requires-Dist: aiohttp
Requires-Dist: asyncer
Requires-Dist: click
Requires-Dist: fastapi
Requires-Dist: filetype
Requires-Dist: gradio
Requires-Dist: python-multipart
Requires-Dist: uvicorn
Requires-Dist: watchdog
Requires-Dist: requests
Provides-Extra: cli
Requires-Dist: aiohttp ; extra == 'cli'
Requires-Dist: asyncer ; extra == 'cli'
Requires-Dist: click ; extra == 'cli'
Requires-Dist: fastapi ; extra == 'cli'
Requires-Dist: filetype ; extra == 'cli'
Requires-Dist: gradio ; extra == 'cli'
Requires-Dist: python-multipart ; extra == 'cli'
Requires-Dist: uvicorn ; extra == 'cli'
Requires-Dist: watchdog ; extra == 'cli'
Provides-Extra: dev
Requires-Dist: bandit ; extra == 'dev'
Requires-Dist: black ; extra == 'dev'
Requires-Dist: flake8 ; extra == 'dev'
Requires-Dist: imagehash ; extra == 'dev'
Requires-Dist: isort ; extra == 'dev'
Requires-Dist: mypy ; extra == 'dev'
Requires-Dist: pytest ; extra == 'dev'
Requires-Dist: setuptools ; extra == 'dev'
Requires-Dist: twine ; extra == 'dev'
Requires-Dist: wheel ; extra == 'dev'
Provides-Extra: gpu
Requires-Dist: onnxruntime-gpu ; extra == 'gpu'
